{
"libraries": [
  {
    "name": "DallasTemperature",
    "version": "3.7.7",
    "author": "Miles Burton \u003cmiles@mnetcs.com\u003e, Tim Newsome <nuisance@casualhacker.net>, Guil Barros <gfbarros@bappos.com>, Rob Tillaart <rob.tillaart@gmail.com>",
    "maintainer": "Martin Mikula \u003cmikula@lmt.sk\u003e",
    "sentence": "Arduino Library for Dallas Temperature ICs (DS18B20, DS18S20, DS1822, DS1820)",
    "paragraph": "",
    "website": "http://www.lmt.sk/arduino",
    "category": "Display",
    "architectures": ["*"
    ],
    "types": [
      "arduino"
    ],
    "url": "http://www.lmt.sk/arduino/DallasTemperature-3.7.7.zip",
    "archiveFileName": "DallasTemperature-3.7.7.zip",
    "size": 29080,
    "checksum": "SHA-256:41f633d58e6946dbfb920070a55dfebae706938675cff1780c294b616f1d1274"
  }
 ,{
    "name": "MemoryFree",
    "version": "1.0.0",
    "author": "Unknown",
    "maintainer": "Martin Mikula \u003cmikula@lmt.sk\u003e",
    "sentence": "This library shows free memory.",
    "paragraph": "",
    "website": "http://www.lmt.sk/arduino",
    "category": "Other",
    "architectures": ["*"
    ],
    "types": [
      "arduino"
    ],
    "url": "http://www.lmt.sk/arduino/MemoryFree-1.0.0.zip",
    "archiveFileName": "MemoryFree-1.0.0.zip",
    "size": 3100,
    "checksum": "SHA-256:5c394d7d68f5356d6a8fd8332b419ea5c08d83e5984c752092625505d16bfac7"
  }

 ,{
    "name": "URTouch",
    "version": "1.2.0",
    "author": "Rinky-Dink Electronics",
    "maintainer": "Martin Mikula \u003cmikula@lmt.sk\u003e",
    "sentence": "This library is primarily an add-on to UTFT library for TFT display modules.",
    "paragraph": "",
    "website": "http://www.lmt.sk/arduino",
    "category": "Display",
    "architectures": [
      "avr","arm","pic32"
    ],
    "types": [
      "arduino"
    ],
    "url": "http://www.lmt.sk/arduino/URTouch-1.2.0.zip",
    "archiveFileName": "URTouch-1.2.0.zip",
    "size": 182806,
    "checksum": "SHA-256:b54cfe140d310337a6ab804d38bce8cf1da360bbf16cc6b32ce8953bb0c6d3f2"
  }
 ,{
    "name": "Utft",
    "version": "2.8.2",
    "author": "Rinky-Dink Electronics",
    "maintainer": "Martin Mikula \u003cmikula@lmt.sk\u003e",
    "sentence": "UTFT library for TFT display modules.",
    "paragraph": "",
    "website": "http://www.lmt.sk/arduino",
    "category": "Display",
    "architectures": [
      "avr","arm","pic32"
    ],
    "types": [
      "arduino"
    ],
    "url": "http://www.lmt.sk/arduino/Utft-2.8.2.zip",
    "archiveFileName": "Utft-2.8.2.zip",
    "size": 2409063,
    "checksum": "SHA-256:299fd76a8e8980ddd9fd893aa7f4fc0c31d53e947938e8d41a63286689d62e65"
  }
 ,{
    "name": "Utft_ArialBold",
    "version": "1.0.0",
    "author": "Rinky-Dink Electronics",
    "maintainer": "Martin Mikula \u003cmikula@lmt.sk\u003e",
    "sentence": "This library is primarily an add-on to UTFT library for TFT display modules.",
    "paragraph": "",
    "website": "http://www.lmt.sk/arduino",
    "category": "Display",
    "architectures": [
      "avr","arm","pic32"
    ],
    "types": [
      "arduino"
    ],
    "url": "http://www.lmt.sk/arduino/Utft_ArialBold-1.0.0.zip",
    "archiveFileName": "Utft_ArialBold-1.0.0.zip",
    "size": 3223,
    "checksum": "SHA-256:48d7908981a20c6be78ed430158f6219adc107dd14638ad8f3d864f64b8b00e3"
  }
 ,{
    "name": "Utft_Buttons",
    "version": "1.0.3",
    "author": "Rinky-Dink Electronics",
    "maintainer": "Martin Mikula \u003cmikula@lmt.sk\u003e",
    "sentence": "This library is primarily an add-on to UTFT library for TFT display modules.",
    "paragraph": "",
    "website": "http://www.lmt.sk/arduino",
    "category": "Display",
    "architectures": [
      "avr","arm","pic32"
    ],
    "types": [
      "arduino"
    ],
    "url": "http://www.lmt.sk/arduino/Utft_Buttons-1.0.3.zip",
    "archiveFileName": "Utft_Buttons-1.0.3.zip",
    "size": 173646,
    "checksum": "SHA-256:9c5fac7abf2aef18fb668cc4cfe2b3dbb56741bcb62cc8464e72ef67c9e6923b"
  }
 ,{
    "name": "Utft_FontSevenSegPlusPlus",
    "version": "1.0.0",
    "author": "Rinky-Dink Electronics",
    "maintainer": "Martin Mikula \u003cmikula@lmt.sk\u003e",
    "sentence": "This library is primarily an add-on to UTFT library for TFT display modules.",
    "paragraph": "",
    "website": "http://www.lmt.sk/arduino",
    "category": "Display",
    "architectures": [
      "avr","arm","pic32"
    ],
    "types": [
      "arduino"
    ],
    "url": "http://www.lmt.sk/arduino/Utft_FontSevenSegPlusPlus-1.0.0.zip",
    "archiveFileName": "Utft_FontSevenSegPlusPlus-1.0.0.zip",
    "size": 4884,
    "checksum": "SHA-256:8cbc05e534c703a7e8660a4f18360cb34848f3fa2703417918e5f7aacea98d88"
  }
 ,{
    "name": "Utft_Geometry",
    "version": "1.0.1",
    "author": "Rinky-Dink Electronics",
    "maintainer": "Martin Mikula \u003cmikula@lmt.sk\u003e",
    "sentence": "This library is primarily an add-on to UTFT library for TFT display modules.",
    "paragraph": "",
    "website": "http://www.lmt.sk/arduino",
    "category": "Display",
    "architectures": [
      "avr","arm","pic32"
    ],
    "types": [
      "arduino"
    ],
    "url": "http://www.lmt.sk/arduino/Utft_Geometry-1.0.1.zip",
    "archiveFileName": "Utft_Geometry-1.0.1.zip",
    "size": 87950,
    "checksum": "SHA-256:b370b6716bb582033d47c473fb19bfb54bdae15c6eae38217bc42f36ea52454e"
  }
]
}
